{
  "health.jpg": {
    "title": "Surgical team in theatre",
    "license": "Pixabay Content License (free for commercial use)",
    "source": "https://pixabay.com/ \u2014 contributor: sasint (image 1807541)"
  },
  "aged-care.jpg": {
    "title": "Carer with an older person in a wheelchair",
    "license": "Pixabay Content License (free for commercial use)",
    "source": "https://pixabay.com/ \u2014 contributor: mrwashingt0n (image 9272780)"
  },
  "mining.jpg": {
    "title": "Bucket-wheel excavator at an open-pit mine",
    "license": "Pixabay Content License (free for commercial use)",
    "source": "https://pixabay.com/ \u2014 image 4359640 (652234)"
  },
  "vet.jpg": {
    "title": "Vet examining a labrador",
    "license": "Pixabay Content License (free for commercial use)",
    "source": "https://pixabay.com/ \u2014 contributor: hansuan_fabregas (image 8434227)"
  },
  "ict.jpg": {
    "title": "Technologist at a control desk (AI-generated)",
    "license": "Pixabay Content License (free for commercial use)",
    "source": "https://pixabay.com/ \u2014 contributor: vilkasss (image 8894581)"
  },
  "allied.jpg": {
    "title": "Manual therapy / physiotherapy session",
    "license": "Pixabay Content License (free for commercial use)",
    "source": "https://pixabay.com/ \u2014 contributor: physiosRus (image 10148280)"
  }
}